spbm/__init__.py
spbm-0.0.1.dist-info/LICENSE
spbm-0.0.1.dist-info/METADATA
spbm-0.0.1.dist-info/WHEEL
spbm-0.0.1.dist-info/top_level.txt
spbm-0.0.1.dist-info/RECORD
