Metadata-Version: 2.1
Name: spbm
Version: 0.0.1
Summary: A set of handful benchmark utilities
Home-page: https://github.com/alchermd/sbmp
Author: John Alcher Doloiras
Author-email: johnalcherdoloiras@gmail.com
License: UNKNOWN
Platform: UNKNOWN
Classifier: Programming Language :: Python :: 3
Classifier: License :: OSI Approved :: MIT License
Classifier: Operating System :: OS Independent
Requires-Python: >=3.6
